MANIFEST.in
README.md
README.rst
pyproject.toml
setup.py
facebook_scraper/__init__.py
facebook_scraper/__main__.py
facebook_scraper/constants.py
facebook_scraper/extractors.py
facebook_scraper/facebook_scraper.py
facebook_scraper/fb_types.py
facebook_scraper/page_iterators.py
facebook_scraper/utils.py
py_facebook_scraper.egg-info/PKG-INFO
py_facebook_scraper.egg-info/SOURCES.txt
py_facebook_scraper.egg-info/dependency_links.txt
py_facebook_scraper.egg-info/top_level.txt