Metadata-Version: 2.1
Name: py-facebook-scraper
Version: 0.2.24
Summary: Facebook-scraper python client package
Home-page: https://gitee.com/evoup/py-facebook-scraper
Author: Madhouse Inc.
Author-email: evoex123@gmail.com
License: UNKNOWN
Platform: UNKNOWN
Classifier: Programming Language :: Python :: 3
Classifier: Operating System :: POSIX :: Linux
